stripe_kong/__init__.py
stripe_kong/admin.py
stripe_kong/admin_views.py
stripe_kong/apps.py
stripe_kong/models.py
stripe_kong/serializers.py
stripe_kong/signals.py
stripe_kong/urls.py
stripe_kong/views.py
stripe_kong/apps/api_management/kong_client.py
stripe_kong/apps/api_management/models.py
stripe_kong/apps/app_builder/models.py
stripe_kong/apps/app_builder/serializers.py
stripe_kong/apps/app_builder/views.py
stripe_kong/apps/payments/admin.py
stripe_kong/apps/payments/serializers.py
stripe_kong/apps/payments/views.py
stripe_kong/management/commands/__init__.py
stripe_kong/management/commands/setup_kong.py
stripe_kong/management/commands/sync_from_kong.py
stripe_kong/management/commands/sync_strip_plans.py
stripe_kong/migrations/0001_initial.py
stripe_kong/migrations/__init__.py
stripe_kong/static/stripe_kong/js/puck/package-lock.json
stripe_kong/static/stripe_kong/js/puck/package.json
stripe_kong/static/stripe_kong/js/puck/src/editor.js
stripe_kong/static/stripe_kong/js/puck/src/renderer.js
stripe_kong/templates/admin/stripe_kong/index.html
stripe_kong/templates/admin/stripe_kong/kong_status.html
stripe_kong/templates/admin/stripe_kong/page.html
stripe_kong/templates/admin/stripe_kong/puckpage/change_form.html
stripe_kong/templates/admin/stripe_kong/puckpage/editor.html
stripe_kong/templates/stripe_kong/checkouts.html
stripe_kong/templates/stripe_kong/page.html
stripe_kong/templates/stripe_kong/success.html
stripe_kong/templates/stripe_kong/puckpage/change_form.html
stripe_kong/utils/__init__.py
stripe_kong/utils/kong_client.py
stripe_kong/utils/stripe_client.py
paybuildr-0.1.0.dist-info/LICENSE
paybuildr-0.1.0.dist-info/METADATA
paybuildr-0.1.0.dist-info/WHEEL
paybuildr-0.1.0.dist-info/top_level.txt
paybuildr-0.1.0.dist-info/RECORD
