Metadata-Version: 2.2
Name: paybuildr
Version: 0.1.0
Summary: A Django app for integrating Stripe payments and Kong API management
Home-page: https://github.com/allen-munsch/paybuildr
Author: James Munsch
Author-email: James Munsch <james.munsch@ccsconsulting.rocks>
Project-URL: Homepage, https://github.com/allen-munsch/paybuildr
Project-URL: Bug Tracker, https://github.com/allen-munsch/paybuildr/issues
Classifier: Environment :: Web Environment
Classifier: Framework :: Django
Classifier: Framework :: Django :: 5.0
Classifier: Intended Audience :: Developers
Classifier: License :: OSI Approved :: MIT License
Classifier: Operating System :: OS Independent
Classifier: Programming Language :: Python
Classifier: Programming Language :: Python :: 3
Classifier: Programming Language :: Python :: 3.12
Classifier: Topic :: Internet :: WWW/HTTP
Requires-Python: >=3.12
License-File: LICENSE
Requires-Dist: Django>=5.0.0
Requires-Dist: djangorestframework>=3.14.0
Requires-Dist: stripe>=7.0.0
Requires-Dist: requests>=2.31.0
Dynamic: author
Dynamic: home-page
Dynamic: requires-python
